{"cameraMode":{"drawMode":0,"name":"Shaded","section":"Shading Mode"},"sceneLighting":true,"audioPlay":false,"sceneViewState":{"m_AlwaysRefresh":false,"showFog":true,"showSkybox":true,"showFlares":true,"showImageEffects":true,"showParticleSystems":true,"showVisualEffectGraphs":true,"m_FxEnabled":true},"in2DMode":false,"pivot":{"x":39.73321533203125,"y":1004.6640625,"z":601.6165771484375},"rotation":{"x":-0.23258106410503388,"y":-0.7574842572212219,"z":0.35471591353416445,"w":-0.4964733123779297},"size":560.1344604492188,"orthographic":true}